export_ease/__init__.py
export_ease/comtrade.py
export_ease/imf.py
export_ease-0.0.9.dist-info/LICENSE
export_ease-0.0.9.dist-info/METADATA
export_ease-0.0.9.dist-info/WHEEL
export_ease-0.0.9.dist-info/top_level.txt
export_ease-0.0.9.dist-info/RECORD
