Metadata-Version: 2.1
Name: export_ease
Version: 0.0.9
Summary: A package that facilitates API calls to UN Comtrade and the International Monetary Fund to gather macroeconomic export data
Author-email: Paul Dilly <paul.dilly@duke.edu>
Project-URL: Homepage, https://github.com/pcd15/export_pkg
Classifier: Programming Language :: Python :: 3
Classifier: License :: OSI Approved :: MIT License
Classifier: Operating System :: OS Independent
Requires-Python: >=3.7
License-File: LICENSE
